timbersnake/__init__.py
timbersnake/client.py
timbersnake/server.py
timbersnake-0.1.0.dist-info/LICENSE
timbersnake-0.1.0.dist-info/METADATA
timbersnake-0.1.0.dist-info/WHEEL
timbersnake-0.1.0.dist-info/top_level.txt
timbersnake-0.1.0.dist-info/RECORD
