Metadata-Version: 2.1
Name: timbersnake
Version: 0.1.0
Summary: Client & server implementation of the lumberjack protocol v1+2 in Python asyncio
Author-email: Matthew Murr <matt@murr.dev>
License: Copyright (c) 2024 Matthew Murr
Project-URL: Homepage, https://git.sr.ht/~murr/timbersnake
Project-URL: Repository, https://git.sr.ht/~murr/timbersnake
Project-URL: Documentation, https://git.sr.ht/~murr/timbersnake/tree/master/item/README.md
Keywords: logstash,lumberjack,beats,filebeat,elastic
Classifier: Development Status :: 4 - Beta
Classifier: Intended Audience :: Developers
Classifier: Programming Language :: Python :: 3
Classifier: License :: OSI Approved :: MIT License
Classifier: Operating System :: OS Independent
Classifier: Topic :: Software Development :: Libraries
Requires-Python: >=3.8
License-File: LICENSE
